CHANGES.txt
MANIFEST.in
README.txt
setup.py
js/__init__.py
js.galleria.egg-info/PKG-INFO
js.galleria.egg-info/SOURCES.txt
js.galleria.egg-info/dependency_links.txt
js.galleria.egg-info/entry_points.txt
js.galleria.egg-info/namespace_packages.txt
js.galleria.egg-info/not-zip-safe
js.galleria.egg-info/requires.txt
js.galleria.egg-info/top_level.txt
js/galleria/__init__.py
js/galleria/test_galleria.txt
js/galleria/resources/galleria.js
js/galleria/resources/galleria.min.js
js/galleria/resources/themes/classic/classic-loader.gif
js/galleria/resources/themes/classic/classic-map.png
js/galleria/resources/themes/classic/galleria.classic.css
js/galleria/resources/themes/classic/galleria.classic.js
js/galleria/resources/themes/classic/galleria.classic.min.js