Metadata-Version: 1.1
Name: js.galleria
Version: 1.2.9-2
Summary: Fanstatic packaging of galleria.js.
Home-page: https://bitbucket.org/it_spirit/js.galleria
Author: Thomas Massmann
Author-email: thomas.massmann@it-spir.it
License: BSD
Download-URL: http://pypi.python.org/pypi/js.galleria
Platform: UNKNOWN
